dpcmaps/__init__.py
dpcmaps/_version.py
dpcmaps/dpc.py
dpcmaps/dpc_batch.py
dpcmaps/dpc_batch_gui.py
dpcmaps/dpc_gui.py
dpcmaps/dpc_kernel.py
dpcmaps/hxn_db.py
dpcmaps/load_timepix.py
dpcmaps/pyspecfile.py
dpcmaps/remove_ctrl_m_chars.py
dpcmaps/scan.py
dpcmaps/cmap_previews/Accent.png
dpcmaps/cmap_previews/Blues.png
dpcmaps/cmap_previews/BrBG.png
dpcmaps/cmap_previews/BuGn.png
dpcmaps/cmap_previews/BuPu.png
dpcmaps/cmap_previews/CMRmap.png
dpcmaps/cmap_previews/Dark2.png
dpcmaps/cmap_previews/GnBu.png
dpcmaps/cmap_previews/Greens.png
dpcmaps/cmap_previews/Greys.png
dpcmaps/cmap_previews/OrRd.png
dpcmaps/cmap_previews/Oranges.png
dpcmaps/cmap_previews/PRGn.png
dpcmaps/cmap_previews/Paired.png
dpcmaps/cmap_previews/Pastel1.png
dpcmaps/cmap_previews/Pastel2.png
dpcmaps/cmap_previews/PiYG.png
dpcmaps/cmap_previews/PuBu.png
dpcmaps/cmap_previews/PuBuGn.png
dpcmaps/cmap_previews/PuOr.png
dpcmaps/cmap_previews/PuRd.png
dpcmaps/cmap_previews/Purples.png
dpcmaps/cmap_previews/RdBu.png
dpcmaps/cmap_previews/RdGy.png
dpcmaps/cmap_previews/RdPu.png
dpcmaps/cmap_previews/RdYlBu.png
dpcmaps/cmap_previews/RdYlGn.png
dpcmaps/cmap_previews/Reds.png
dpcmaps/cmap_previews/Set1.png
dpcmaps/cmap_previews/Set2.png
dpcmaps/cmap_previews/Set3.png
dpcmaps/cmap_previews/Spectral.png
dpcmaps/cmap_previews/Wistia.png
dpcmaps/cmap_previews/YlGn.png
dpcmaps/cmap_previews/YlGnBu.png
dpcmaps/cmap_previews/YlOrBr.png
dpcmaps/cmap_previews/YlOrRd.png
dpcmaps/cmap_previews/afmhot.png
dpcmaps/cmap_previews/autumn.png
dpcmaps/cmap_previews/binary.png
dpcmaps/cmap_previews/bone.png
dpcmaps/cmap_previews/brg.png
dpcmaps/cmap_previews/bwr.png
dpcmaps/cmap_previews/cool.png
dpcmaps/cmap_previews/coolwarm.png
dpcmaps/cmap_previews/copper.png
dpcmaps/cmap_previews/cubehelix.png
dpcmaps/cmap_previews/flag.png
dpcmaps/cmap_previews/gist_earth.png
dpcmaps/cmap_previews/gist_gray.png
dpcmaps/cmap_previews/gist_heat.png
dpcmaps/cmap_previews/gist_ncar.png
dpcmaps/cmap_previews/gist_rainbow.png
dpcmaps-1.1.6.dist-info/AUTHORS.rst
dpcmaps-1.1.6.dist-info/LICENSE
dpcmaps-1.1.6.dist-info/METADATA
dpcmaps-1.1.6.dist-info/WHEEL
dpcmaps-1.1.6.dist-info/entry_points.txt
dpcmaps-1.1.6.dist-info/top_level.txt
dpcmaps-1.1.6.dist-info/RECORD
